{
    "hours": [
        {
            "time": "2022-01-06T00:00:00+00:00",
            "windSpeed": {
                "icon": 3.64,
                "noaa": 3.68,
                "sg": 3.64
            }
        },
        {
            "time": "2022-01-06T01:00:00+00:00",
            "windSpeed": {
                "icon": 3.41,
                "noaa": 3.07,
                "sg": 3.41
            }
        },
        {
            "time": "2022-01-06T02:00:00+00:00",
            "windSpeed": {
                "icon": 3.18,
                "noaa": 2.46,
                "sg": 3.18
            }
        },
        {
            "time": "2022-01-06T03:00:00+00:00",
            "windSpeed": {
                "icon": 2.95,
                "noaa": 1.85,
                "sg": 2.95
            }
        },
        {
            "time": "2022-01-06T04:00:00+00:00",
            "windSpeed": {
                "icon": 2.58,
                "noaa": 1.8,
                "sg": 2.58
            }
        },
        {
            "time": "2022-01-06T05:00:00+00:00",
            "windSpeed": {
                "icon": 2.21,
                "noaa": 1.76,
                "sg": 2.21
            }
        },
        {
            "time": "2022-01-06T06:00:00+00:00",
            "windSpeed": {
                "icon": 1.84,
                "noaa": 1.71,
                "sg": 1.84
            }
        },
        {
            "time": "2022-01-06T07:00:00+00:00",
            "windSpeed": {
                "icon": 2.74,
                "noaa": 2.46,
                "sg": 2.74
            }
        },
        {
            "time": "2022-01-06T08:00:00+00:00",
            "windSpeed": {
                "icon": 3.65,
                "noaa": 3.21,
                "sg": 3.65
            }
        },
        {
            "time": "2022-01-06T09:00:00+00:00",
            "windSpeed": {
                "icon": 4.55,
                "noaa": 3.96,
                "sg": 4.55
            }
        },
        {
            "time": "2022-01-06T10:00:00+00:00",
            "windSpeed": {
                "icon": 5.42,
                "noaa": 4.8,
                "sg": 5.42
            }
        },
        {
            "time": "2022-01-06T11:00:00+00:00",
            "windSpeed": {
                "icon": 6.29,
                "noaa": 5.63,
                "sg": 6.29
            }
        },
        {
            "time": "2022-01-06T12:00:00+00:00",
            "windSpeed": {
                "icon": 7.16,
                "noaa": 6.47,
                "sg": 7.16
            }
        },
        {
            "time": "2022-01-06T13:00:00+00:00",
            "windSpeed": {
                "icon": 7.68,
                "noaa": 7.54,
                "sg": 7.68
            }
        },
        {
            "time": "2022-01-06T14:00:00+00:00",
            "windSpeed": {
                "icon": 8.2,
                "noaa": 8.6,
                "sg": 8.2
            }
        },
        {
            "time": "2022-01-06T15:00:00+00:00",
            "windSpeed": {
                "icon": 8.72,
                "noaa": 9.67,
                "sg": 8.72
            }
        },
        {
            "time": "2022-01-06T16:00:00+00:00",
            "windSpeed": {
                "icon": 9.29,
                "noaa": 10.11,
                "sg": 9.29
            }
        },
        {
            "time": "2022-01-06T17:00:00+00:00",
            "windSpeed": {
                "icon": 9.86,
                "noaa": 10.54,
                "sg": 9.86
            }
        },
        {
            "time": "2022-01-06T18:00:00+00:00",
            "windSpeed": {
                "icon": 10.43,
                "noaa": 10.98,
                "sg": 10.43
            }
        },
        {
            "time": "2022-01-06T19:00:00+00:00",
            "windSpeed": {
                "icon": 10.85,
                "noaa": 11.7,
                "sg": 10.85
            }
        },
        {
            "time": "2022-01-06T20:00:00+00:00",
            "windSpeed": {
                "icon": 11.27,
                "noaa": 12.42,
                "sg": 11.27
            }
        },
        {
            "time": "2022-01-06T21:00:00+00:00",
            "windSpeed": {
                "icon": 11.69,
                "noaa": 13.14,
                "sg": 11.69
            }
        },
        {
            "time": "2022-01-06T22:00:00+00:00",
            "windSpeed": {
                "icon": 11.44,
                "noaa": 12.34,
                "sg": 11.44
            }
        },
        {
            "time": "2022-01-06T23:00:00+00:00",
            "windSpeed": {
                "icon": 11.18,
                "noaa": 11.53,
                "sg": 11.18
            }
        },
        {
            "time": "2022-01-07T00:00:00+00:00",
            "windSpeed": {
                "icon": 10.93,
                "noaa": 10.73,
                "sg": 10.93
            }
        },
        {
            "time": "2022-01-07T01:00:00+00:00",
            "windSpeed": {
                "icon": 9.94,
                "noaa": 11.03,
                "sg": 9.94
            }
        },
        {
            "time": "2022-01-07T02:00:00+00:00",
            "windSpeed": {
                "icon": 8.96,
                "noaa": 11.33,
                "sg": 8.96
            }
        },
        {
            "time": "2022-01-07T03:00:00+00:00",
            "windSpeed": {
                "icon": 7.97,
                "noaa": 11.63,
                "sg": 7.97
            }
        },
        {
            "time": "2022-01-07T04:00:00+00:00",
            "windSpeed": {
                "icon": 8.51,
                "noaa": 11.69,
                "sg": 8.51
            }
        },
        {
            "time": "2022-01-07T05:00:00+00:00",
            "windSpeed": {
                "icon": 9.05,
                "noaa": 11.74,
                "sg": 9.05
            }
        },
        {
            "time": "2022-01-07T06:00:00+00:00",
            "windSpeed": {
                "icon": 9.59,
                "noaa": 11.8,
                "sg": 9.59
            }
        },
        {
            "time": "2022-01-07T07:00:00+00:00",
            "windSpeed": {
                "icon": 9.86,
                "noaa": 12.57,
                "sg": 9.86
            }
        },
        {
            "time": "2022-01-07T08:00:00+00:00",
            "windSpeed": {
                "icon": 10.14,
                "noaa": 13.34,
                "sg": 10.14
            }
        },
        {
            "time": "2022-01-07T09:00:00+00:00",
            "windSpeed": {
                "icon": 10.41,
                "noaa": 14.11,
                "sg": 10.41
            }
        },
        {
            "time": "2022-01-07T10:00:00+00:00",
            "windSpeed": {
                "icon": 10.18,
                "noaa": 13.61,
                "sg": 10.18
            }
        },
        {
            "time": "2022-01-07T11:00:00+00:00",
            "windSpeed": {
                "icon": 9.95,
                "noaa": 13.1,
                "sg": 9.95
            }
        },
        {
            "time": "2022-01-07T12:00:00+00:00",
            "windSpeed": {
                "icon": 9.72,
                "noaa": 12.6,
                "sg": 9.72
            }
        },
        {
            "time": "2022-01-07T13:00:00+00:00",
            "windSpeed": {
                "icon": 9.74,
                "noaa": 11.26,
                "sg": 9.74
            }
        },
        {
            "time": "2022-01-07T14:00:00+00:00",
            "windSpeed": {
                "icon": 9.77,
                "noaa": 9.91,
                "sg": 9.77
            }
        },
        {
            "time": "2022-01-07T15:00:00+00:00",
            "windSpeed": {
                "icon": 9.79,
                "noaa": 8.57,
                "sg": 9.79
            }
        },
        {
            "time": "2022-01-07T16:00:00+00:00",
            "windSpeed": {
                "icon": 10.03,
                "noaa": 10.66,
                "sg": 10.03
            }
        },
        {
            "time": "2022-01-07T17:00:00+00:00",
            "windSpeed": {
                "icon": 10.27,
                "noaa": 12.75,
                "sg": 10.27
            }
        },
        {
            "time": "2022-01-07T18:00:00+00:00",
            "windSpeed": {
                "icon": 10.51,
                "noaa": 14.84,
                "sg": 10.51
            }
        },
        {
            "time": "2022-01-07T19:00:00+00:00",
            "windSpeed": {
                "icon": 8.86,
                "noaa": 13.0,
                "sg": 8.86
            }
        },
        {
            "time": "2022-01-07T20:00:00+00:00",
            "windSpeed": {
                "icon": 7.2,
                "noaa": 11.17,
                "sg": 7.2
            }
        },
        {
            "time": "2022-01-07T21:00:00+00:00",
            "windSpeed": {
                "icon": 5.55,
                "noaa": 9.33,
                "sg": 5.55
            }
        },
        {
            "time": "2022-01-07T22:00:00+00:00",
            "windSpeed": {
                "icon": 5.44,
                "noaa": 8.86,
                "sg": 5.44
            }
        },
        {
            "time": "2022-01-07T23:00:00+00:00",
            "windSpeed": {
                "icon": 5.33,
                "noaa": 8.39,
                "sg": 5.33
            }
        },
        {
            "time": "2022-01-08T00:00:00+00:00",
            "windSpeed": {
                "icon": 5.22,
                "noaa": 7.92,
                "sg": 5.22
            }
        },
        {
            "time": "2022-01-08T01:00:00+00:00",
            "windSpeed": {
                "icon": 5.67,
                "noaa": 7.3,
                "sg": 5.67
            }
        },
        {
            "time": "2022-01-08T02:00:00+00:00",
            "windSpeed": {
                "icon": 6.13,
                "noaa": 6.69,
                "sg": 6.13
            }
        },
        {
            "time": "2022-01-08T03:00:00+00:00",
            "windSpeed": {
                "icon": 6.58,
                "noaa": 6.07,
                "sg": 6.58
            }
        },
        {
            "time": "2022-01-08T04:00:00+00:00",
            "windSpeed": {
                "icon": 7.15,
                "noaa": 6.9,
                "sg": 7.15
            }
        },
        {
            "time": "2022-01-08T05:00:00+00:00",
            "windSpeed": {
                "icon": 7.71,
                "noaa": 7.73,
                "sg": 7.71
            }
        },
        {
            "time": "2022-01-08T06:00:00+00:00",
            "windSpeed": {
                "icon": 8.28,
                "noaa": 8.56,
                "sg": 8.28
            }
        },
        {
            "time": "2022-01-08T07:00:00+00:00",
            "windSpeed": {
                "icon": 9.25,
                "noaa": 9.71,
                "sg": 9.25
            }
        },
        {
            "time": "2022-01-08T08:00:00+00:00",
            "windSpeed": {
                "icon": 10.21,
                "noaa": 10.86,
                "sg": 10.21
            }
        },
        {
            "time": "2022-01-08T09:00:00+00:00",
            "windSpeed": {
                "icon": 11.18,
                "noaa": 12.01,
                "sg": 11.18
            }
        },
        {
            "time": "2022-01-08T10:00:00+00:00",
            "windSpeed": {
                "icon": 11.48,
                "noaa": 12.63,
                "sg": 11.48
            }
        },
        {
            "time": "2022-01-08T11:00:00+00:00",
            "windSpeed": {
                "icon": 11.77,
                "noaa": 13.24,
                "sg": 11.77
            }
        },
        {
            "time": "2022-01-08T12:00:00+00:00",
            "windSpeed": {
                "icon": 12.07,
                "noaa": 13.86,
                "sg": 12.07
            }
        },
        {
            "time": "2022-01-08T13:00:00+00:00",
            "windSpeed": {
                "icon": 12.43,
                "noaa": 13.83,
                "sg": 12.43
            }
        },
        {
            "time": "2022-01-08T14:00:00+00:00",
            "windSpeed": {
                "icon": 12.78,
                "noaa": 13.81,
                "sg": 12.78
            }
        },
        {
            "time": "2022-01-08T15:00:00+00:00",
            "windSpeed": {
                "icon": 13.14,
                "noaa": 13.78,
                "sg": 13.14
            }
        },
        {
            "time": "2022-01-08T16:00:00+00:00",
            "windSpeed": {
                "icon": 12.86,
                "noaa": 14.75,
                "sg": 12.86
            }
        },
        {
            "time": "2022-01-08T17:00:00+00:00",
            "windSpeed": {
                "icon": 12.58,
                "noaa": 15.72,
                "sg": 12.58
            }
        },
        {
            "time": "2022-01-08T18:00:00+00:00",
            "windSpeed": {
                "icon": 12.3,
                "noaa": 16.69,
                "sg": 12.3
            }
        },
        {
            "time": "2022-01-08T19:00:00+00:00",
            "windSpeed": {
                "icon": 12.8,
                "noaa": 16.46,
                "sg": 12.8
            }
        },
        {
            "time": "2022-01-08T20:00:00+00:00",
            "windSpeed": {
                "icon": 13.29,
                "noaa": 16.23,
                "sg": 13.29
            }
        },
        {
            "time": "2022-01-08T21:00:00+00:00",
            "windSpeed": {
                "icon": 13.79,
                "noaa": 16.0,
                "sg": 13.79
            }
        },
        {
            "time": "2022-01-08T22:00:00+00:00",
            "windSpeed": {
                "icon": 13.33,
                "noaa": 15.67,
                "sg": 13.33
            }
        },
        {
            "time": "2022-01-08T23:00:00+00:00",
            "windSpeed": {
                "icon": 12.86,
                "noaa": 15.34,
                "sg": 12.86
            }
        },
        {
            "time": "2022-01-09T00:00:00+00:00",
            "windSpeed": {
                "icon": 12.4,
                "noaa": 15.01,
                "sg": 12.4
            }
        },
        {
            "time": "2022-01-09T01:00:00+00:00",
            "windSpeed": {
                "icon": 11.7,
                "noaa": 14.44,
                "sg": 11.7
            }
        },
        {
            "time": "2022-01-09T02:00:00+00:00",
            "windSpeed": {
                "icon": 11.01,
                "noaa": 13.86,
                "sg": 11.01
            }
        },
        {
            "time": "2022-01-09T03:00:00+00:00",
            "windSpeed": {
                "icon": 10.31,
                "noaa": 13.29,
                "sg": 10.31
            }
        },
        {
            "time": "2022-01-09T04:00:00+00:00",
            "windSpeed": {
                "icon": 10.14,
                "noaa": 12.89,
                "sg": 10.14
            }
        },
        {
            "time": "2022-01-09T05:00:00+00:00",
            "windSpeed": {
                "icon": 9.98,
                "noaa": 12.48,
                "sg": 9.98
            }
        },
        {
            "time": "2022-01-09T06:00:00+00:00",
            "windSpeed": {
                "icon": 9.81,
                "noaa": 12.08,
                "sg": 9.81
            }
        },
        {
            "time": "2022-01-09T07:00:00+00:00",
            "windSpeed": {
                "icon": 9.24,
                "noaa": 12.01,
                "sg": 9.24
            }
        },
        {
            "time": "2022-01-09T08:00:00+00:00",
            "windSpeed": {
                "icon": 8.67,
                "noaa": 11.93,
                "sg": 8.67
            }
        },
        {
            "time": "2022-01-09T09:00:00+00:00",
            "windSpeed": {
                "icon": 8.1,
                "noaa": 11.86,
                "sg": 8.1
            }
        },
        {
            "time": "2022-01-09T10:00:00+00:00",
            "windSpeed": {
                "icon": 7.62,
                "noaa": 11.8,
                "sg": 7.62
            }
        },
        {
            "time": "2022-01-09T11:00:00+00:00",
            "windSpeed": {
                "icon": 7.13,
                "noaa": 11.75,
                "sg": 7.13
            }
        },
        {
            "time": "2022-01-09T12:00:00+00:00",
            "windSpeed": {
                "icon": 6.65,
                "noaa": 11.69,
                "sg": 6.65
            }
        },
        {
            "time": "2022-01-09T13:00:00+00:00",
            "windSpeed": {
                "icon": 6.25,
                "noaa": 11.96,
                "sg": 6.25
            }
        },
        {
            "time": "2022-01-09T14:00:00+00:00",
            "windSpeed": {
                "icon": 5.85,
                "noaa": 12.22,
                "sg": 5.85
            }
        },
        {
            "time": "2022-01-09T15:00:00+00:00",
            "windSpeed": {
                "icon": 5.45,
                "noaa": 12.49,
                "sg": 5.45
            }
        },
        {
            "time": "2022-01-09T16:00:00+00:00",
            "windSpeed": {
                "icon": 5.03,
                "noaa": 12.16,
                "sg": 5.03
            }
        },
        {
            "time": "2022-01-09T17:00:00+00:00",
            "windSpeed": {
                "icon": 4.61,
                "noaa": 11.82,
                "sg": 4.61
            }
        },
        {
            "time": "2022-01-09T18:00:00+00:00",
            "windSpeed": {
                "icon": 4.19,
                "noaa": 11.49,
                "sg": 4.19
            }
        },
        {
            "time": "2022-01-09T19:00:00+00:00",
            "windSpeed": {
                "icon": 3.39,
                "noaa": 11.51,
                "sg": 3.39
            }
        },
        {
            "time": "2022-01-09T20:00:00+00:00",
            "windSpeed": {
                "icon": 2.6,
                "noaa": 11.54,
                "sg": 2.6
            }
        },
        {
            "time": "2022-01-09T21:00:00+00:00",
            "windSpeed": {
                "icon": 1.8,
                "noaa": 11.56,
                "sg": 1.8
            }
        },
        {
            "time": "2022-01-09T22:00:00+00:00",
            "windSpeed": {
                "icon": 2.44,
                "noaa": 10.91,
                "sg": 2.44
            }
        },
        {
            "time": "2022-01-09T23:00:00+00:00",
            "windSpeed": {
                "icon": 3.09,
                "noaa": 10.26,
                "sg": 3.09
            }
        },
        {
            "time": "2022-01-10T00:00:00+00:00",
            "windSpeed": {
                "icon": 3.73,
                "noaa": 9.61,
                "sg": 3.73
            }
        },
        {
            "time": "2022-01-10T01:00:00+00:00",
            "windSpeed": {
                "icon": 3.79,
                "noaa": 8.87,
                "sg": 3.79
            }
        },
        {
            "time": "2022-01-10T02:00:00+00:00",
            "windSpeed": {
                "icon": 3.84,
                "noaa": 8.12,
                "sg": 3.84
            }
        },
        {
            "time": "2022-01-10T03:00:00+00:00",
            "windSpeed": {
                "icon": 3.9,
                "noaa": 7.38,
                "sg": 3.9
            }
        },
        {
            "time": "2022-01-10T04:00:00+00:00",
            "windSpeed": {
                "icon": 3.97,
                "noaa": 6.65,
                "sg": 3.97
            }
        },
        {
            "time": "2022-01-10T05:00:00+00:00",
            "windSpeed": {
                "icon": 4.03,
                "noaa": 5.91,
                "sg": 4.03
            }
        },
        {
            "time": "2022-01-10T06:00:00+00:00",
            "windSpeed": {
                "icon": 4.1,
                "noaa": 5.18,
                "sg": 4.1
            }
        },
        {
            "time": "2022-01-10T07:00:00+00:00",
            "windSpeed": {
                "icon": 3.84,
                "noaa": 4.56,
                "sg": 3.84
            }
        },
        {
            "time": "2022-01-10T08:00:00+00:00",
            "windSpeed": {
                "icon": 3.57,
                "noaa": 3.95,
                "sg": 3.57
            }
        },
        {
            "time": "2022-01-10T09:00:00+00:00",
            "windSpeed": {
                "icon": 3.31,
                "noaa": 3.33,
                "sg": 3.31
            }
        },
        {
            "time": "2022-01-10T10:00:00+00:00",
            "windSpeed": {
                "icon": 3.1,
                "noaa": 3.03,
                "sg": 3.1
            }
        },
        {
            "time": "2022-01-10T11:00:00+00:00",
            "windSpeed": {
                "icon": 2.88,
                "noaa": 2.74,
                "sg": 2.88
            }
        },
        {
            "time": "2022-01-10T12:00:00+00:00",
            "windSpeed": {
                "icon": 2.67,
                "noaa": 2.44,
                "sg": 2.67
            }
        },
        {
            "time": "2022-01-10T13:00:00+00:00",
            "windSpeed": {
                "icon": 3.15,
                "noaa": 2.46,
                "sg": 3.15
            }
        },
        {
            "time": "2022-01-10T14:00:00+00:00",
            "windSpeed": {
                "icon": 3.64,
                "noaa": 2.48,
                "sg": 3.64
            }
        },
        {
            "time": "2022-01-10T15:00:00+00:00",
            "windSpeed": {
                "icon": 4.12,
                "noaa": 2.5,
                "sg": 4.12
            }
        },
        {
            "time": "2022-01-10T16:00:00+00:00",
            "windSpeed": {
                "icon": 4.08,
                "noaa": 2.95,
                "sg": 4.08
            }
        },
        {
            "time": "2022-01-10T17:00:00+00:00",
            "windSpeed": {
                "icon": 4.04,
                "noaa": 3.4,
                "sg": 4.04
            }
        },
        {
            "time": "2022-01-10T18:00:00+00:00",
            "windSpeed": {
                "icon": 4.0,
                "noaa": 3.85,
                "sg": 4.0
            }
        },
        {
            "time": "2022-01-10T19:00:00+00:00",
            "windSpeed": {
                "icon": 4.02,
                "noaa": 4.2,
                "sg": 4.02
            }
        },
        {
            "time": "2022-01-10T20:00:00+00:00",
            "windSpeed": {
                "icon": 4.03,
                "noaa": 4.54,
                "sg": 4.03
            }
        },
        {
            "time": "2022-01-10T21:00:00+00:00",
            "windSpeed": {
                "icon": 4.05,
                "noaa": 4.89,
                "sg": 4.05
            }
        },
        {
            "time": "2022-01-10T22:00:00+00:00",
            "windSpeed": {
                "icon": 3.79,
                "noaa": 5.17,
                "sg": 3.79
            }
        },
        {
            "time": "2022-01-10T23:00:00+00:00",
            "windSpeed": {
                "icon": 3.54,
                "noaa": 5.45,
                "sg": 3.54
            }
        },
        {
            "time": "2022-01-11T00:00:00+00:00",
            "windSpeed": {
                "icon": 3.28,
                "noaa": 5.73,
                "sg": 3.28
            }
        },
        {
            "time": "2022-01-11T01:00:00+00:00",
            "windSpeed": {
                "icon": 3.51,
                "noaa": 5.61,
                "sg": 3.51
            }
        },
        {
            "time": "2022-01-11T02:00:00+00:00",
            "windSpeed": {
                "icon": 3.74,
                "noaa": 5.49,
                "sg": 3.74
            }
        },
        {
            "time": "2022-01-11T03:00:00+00:00",
            "windSpeed": {
                "icon": 3.96,
                "noaa": 5.37,
                "sg": 3.96
            }
        },
        {
            "time": "2022-01-11T04:00:00+00:00",
            "windSpeed": {
                "icon": 3.85,
                "noaa": 5.33,
                "sg": 3.85
            }
        },
        {
            "time": "2022-01-11T05:00:00+00:00",
            "windSpeed": {
                "icon": 3.73,
                "noaa": 5.28,
                "sg": 3.73
            }
        },
        {
            "time": "2022-01-11T06:00:00+00:00",
            "windSpeed": {
                "icon": 3.62,
                "noaa": 5.24,
                "sg": 3.62
            }
        },
        {
            "time": "2022-01-11T07:00:00+00:00",
            "windSpeed": {
                "icon": 3.53,
                "noaa": 4.97,
                "sg": 3.53
            }
        },
        {
            "time": "2022-01-11T08:00:00+00:00",
            "windSpeed": {
                "icon": 3.43,
                "noaa": 4.7,
                "sg": 3.43
            }
        },
        {
            "time": "2022-01-11T09:00:00+00:00",
            "windSpeed": {
                "icon": 3.34,
                "noaa": 4.43,
                "sg": 3.34
            }
        },
        {
            "time": "2022-01-11T10:00:00+00:00",
            "windSpeed": {
                "icon": 3.41,
                "noaa": 4.23,
                "sg": 3.41
            }
        },
        {
            "time": "2022-01-11T11:00:00+00:00",
            "windSpeed": {
                "icon": 3.47,
                "noaa": 4.03,
                "sg": 3.47
            }
        },
        {
            "time": "2022-01-11T12:00:00+00:00",
            "windSpeed": {
                "icon": 3.54,
                "noaa": 3.83,
                "sg": 3.54
            }
        },
        {
            "time": "2022-01-11T13:00:00+00:00",
            "windSpeed": {
                "icon": 3.23,
                "noaa": 3.66,
                "sg": 3.23
            }
        },
        {
            "time": "2022-01-11T14:00:00+00:00",
            "windSpeed": {
                "icon": 2.91,
                "noaa": 3.49,
                "sg": 2.91
            }
        },
        {
            "time": "2022-01-11T15:00:00+00:00",
            "windSpeed": {
                "icon": 2.6,
                "noaa": 3.32,
                "sg": 2.6
            }
        },
        {
            "time": "2022-01-11T16:00:00+00:00",
            "windSpeed": {
                "icon": 2.4,
                "noaa": 3.82,
                "sg": 2.4
            }
        },
        {
            "time": "2022-01-11T17:00:00+00:00",
            "windSpeed": {
                "icon": 2.21,
                "noaa": 4.31,
                "sg": 2.21
            }
        },
        {
            "time": "2022-01-11T18:00:00+00:00",
            "windSpeed": {
                "icon": 2.01,
                "noaa": 4.81,
                "sg": 2.01
            }
        },
        {
            "time": "2022-01-11T19:00:00+00:00",
            "windSpeed": {
                "icon": 2.47,
                "noaa": 5.03,
                "sg": 2.47
            }
        },
        {
            "time": "2022-01-11T20:00:00+00:00",
            "windSpeed": {
                "icon": 2.94,
                "noaa": 5.25,
                "sg": 2.94
            }
        },
        {
            "time": "2022-01-11T21:00:00+00:00",
            "windSpeed": {
                "icon": 3.4,
                "noaa": 5.47,
                "sg": 3.4
            }
        },
        {
            "time": "2022-01-11T22:00:00+00:00",
            "windSpeed": {
                "icon": 3.37,
                "noaa": 5.41,
                "sg": 3.37
            }
        },
        {
            "time": "2022-01-11T23:00:00+00:00",
            "windSpeed": {
                "icon": 3.35,
                "noaa": 5.36,
                "sg": 3.35
            }
        },
        {
            "time": "2022-01-12T00:00:00+00:00",
            "windSpeed": {
                "icon": 3.32,
                "noaa": 5.3,
                "sg": 3.32
            }
        },
        {
            "time": "2022-01-12T01:00:00+00:00",
            "windSpeed": {
                "icon": 3.3,
                "noaa": 5.65,
                "sg": 3.3
            }
        },
        {
            "time": "2022-01-12T02:00:00+00:00",
            "windSpeed": {
                "icon": 3.29,
                "noaa": 5.99,
                "sg": 3.29
            }
        },
        {
            "time": "2022-01-12T03:00:00+00:00",
            "windSpeed": {
                "icon": 3.27,
                "noaa": 6.34,
                "sg": 3.27
            }
        },
        {
            "time": "2022-01-12T04:00:00+00:00",
            "windSpeed": {
                "icon": 3.03,
                "noaa": 6.58,
                "sg": 3.03
            }
        },
        {
            "time": "2022-01-12T05:00:00+00:00",
            "windSpeed": {
                "icon": 2.8,
                "noaa": 6.81,
                "sg": 2.8
            }
        },
        {
            "time": "2022-01-12T06:00:00+00:00",
            "windSpeed": {
                "icon": 2.56,
                "noaa": 7.05,
                "sg": 2.56
            }
        },
        {
            "time": "2022-01-12T07:00:00+00:00",
            "windSpeed": {
                "icon": 2.42,
                "noaa": 7.12,
                "sg": 2.42
            }
        },
        {
            "time": "2022-01-12T08:00:00+00:00",
            "windSpeed": {
                "icon": 2.28,
                "noaa": 7.19,
                "sg": 2.28
            }
        },
        {
            "time": "2022-01-12T09:00:00+00:00",
            "windSpeed": {
                "icon": 2.14,
                "noaa": 7.26,
                "sg": 2.14
            }
        },
        {
            "time": "2022-01-12T10:00:00+00:00",
            "windSpeed": {
                "icon": 2.03,
                "noaa": 7.47,
                "sg": 2.03
            }
        },
        {
            "time": "2022-01-12T11:00:00+00:00",
            "windSpeed": {
                "icon": 1.92,
                "noaa": 7.69,
                "sg": 1.92
            }
        },
        {
            "time": "2022-01-12T12:00:00+00:00",
            "windSpeed": {
                "icon": 1.8,
                "noaa": 7.9,
                "sg": 1.8
            }
        },
        {
            "time": "2022-01-12T13:00:00+00:00",
            "windSpeed": {
                "icon": 1.84,
                "noaa": 8.11,
                "sg": 1.84
            }
        },
        {
            "time": "2022-01-12T14:00:00+00:00",
            "windSpeed": {
                "icon": 1.88,
                "noaa": 8.33,
                "sg": 1.88
            }
        },
        {
            "time": "2022-01-12T15:00:00+00:00",
            "windSpeed": {
                "icon": 1.92,
                "noaa": 8.54,
                "sg": 1.92
            }
        },
        {
            "time": "2022-01-12T16:00:00+00:00",
            "windSpeed": {
                "icon": 2.05,
                "noaa": 8.63,
                "sg": 2.05
            }
        },
        {
            "time": "2022-01-12T17:00:00+00:00",
            "windSpeed": {
                "icon": 2.17,
                "noaa": 8.73,
                "sg": 2.17
            }
        },
        {
            "time": "2022-01-12T18:00:00+00:00",
            "windSpeed": {
                "icon": 2.3,
                "noaa": 8.82,
                "sg": 2.3
            }
        },
        {
            "time": "2022-01-12T19:00:00+00:00",
            "windSpeed": {
                "icon": 2.49,
                "noaa": 8.92,
                "sg": 2.49
            }
        },
        {
            "time": "2022-01-12T20:00:00+00:00",
            "windSpeed": {
                "icon": 2.67,
                "noaa": 9.02,
                "sg": 2.67
            }
        },
        {
            "time": "2022-01-12T21:00:00+00:00",
            "windSpeed": {
                "icon": 2.86,
                "noaa": 9.12,
                "sg": 2.86
            }
        },
        {
            "time": "2022-01-12T22:00:00+00:00",
            "windSpeed": {
                "icon": 3.15,
                "noaa": 9.03,
                "sg": 3.15
            }
        },
        {
            "time": "2022-01-12T23:00:00+00:00",
            "windSpeed": {
                "icon": 3.44,
                "noaa": 8.95,
                "sg": 3.44
            }
        },
        {
            "time": "2022-01-13T00:00:00+00:00",
            "windSpeed": {
                "icon": 3.73,
                "noaa": 8.86,
                "sg": 3.73
            }
        },
        {
            "time": "2022-01-13T01:00:00+00:00",
            "windSpeed": {
                "icon": 3.79,
                "noaa": 8.74,
                "sg": 3.79
            }
        },
        {
            "time": "2022-01-13T02:00:00+00:00",
            "windSpeed": {
                "icon": 3.85,
                "noaa": 8.62,
                "sg": 3.85
            }
        },
        {
            "time": "2022-01-13T03:00:00+00:00",
            "windSpeed": {
                "icon": 3.91,
                "noaa": 8.5,
                "sg": 3.91
            }
        },
        {
            "time": "2022-01-13T04:00:00+00:00",
            "windSpeed": {
                "icon": 3.79,
                "noaa": 8.6,
                "sg": 3.79
            }
        },
        {
            "time": "2022-01-13T05:00:00+00:00",
            "windSpeed": {
                "icon": 3.66,
                "noaa": 8.69,
                "sg": 3.66
            }
        },
        {
            "time": "2022-01-13T06:00:00+00:00",
            "windSpeed": {
                "icon": 3.54,
                "noaa": 8.79,
                "sg": 3.54
            }
        },
        {
            "time": "2022-01-13T07:00:00+00:00",
            "windSpeed": {
                "noaa": 8.63,
                "sg": 8.63
            }
        },
        {
            "time": "2022-01-13T08:00:00+00:00",
            "windSpeed": {
                "noaa": 8.48,
                "sg": 8.48
            }
        },
        {
            "time": "2022-01-13T09:00:00+00:00",
            "windSpeed": {
                "noaa": 8.32,
                "sg": 8.32
            }
        },
        {
            "time": "2022-01-13T10:00:00+00:00",
            "windSpeed": {
                "noaa": 7.84,
                "sg": 7.84
            }
        },
        {
            "time": "2022-01-13T11:00:00+00:00",
            "windSpeed": {
                "noaa": 7.36,
                "sg": 7.36
            }
        },
        {
            "time": "2022-01-13T12:00:00+00:00",
            "windSpeed": {
                "noaa": 6.88,
                "sg": 6.88
            }
        },
        {
            "time": "2022-01-13T13:00:00+00:00",
            "windSpeed": {
                "noaa": 6.89,
                "sg": 6.89
            }
        },
        {
            "time": "2022-01-13T14:00:00+00:00",
            "windSpeed": {
                "noaa": 6.9,
                "sg": 6.9
            }
        },
        {
            "time": "2022-01-13T15:00:00+00:00",
            "windSpeed": {
                "noaa": 6.91,
                "sg": 6.91
            }
        },
        {
            "time": "2022-01-13T16:00:00+00:00",
            "windSpeed": {
                "noaa": 7.1,
                "sg": 7.1
            }
        },
        {
            "time": "2022-01-13T17:00:00+00:00",
            "windSpeed": {
                "noaa": 7.29,
                "sg": 7.29
            }
        },
        {
            "time": "2022-01-13T18:00:00+00:00",
            "windSpeed": {
                "noaa": 7.48,
                "sg": 7.48
            }
        },
        {
            "time": "2022-01-13T19:00:00+00:00",
            "windSpeed": {
                "noaa": 7.23,
                "sg": 7.23
            }
        },
        {
            "time": "2022-01-13T20:00:00+00:00",
            "windSpeed": {
                "noaa": 6.97,
                "sg": 6.97
            }
        },
        {
            "time": "2022-01-13T21:00:00+00:00",
            "windSpeed": {
                "noaa": 6.72,
                "sg": 6.72
            }
        },
        {
            "time": "2022-01-13T22:00:00+00:00",
            "windSpeed": {
                "noaa": 6.81,
                "sg": 6.81
            }
        },
        {
            "time": "2022-01-13T23:00:00+00:00",
            "windSpeed": {
                "noaa": 6.9,
                "sg": 6.9
            }
        },
        {
            "time": "2022-01-14T00:00:00+00:00",
            "windSpeed": {
                "noaa": 6.99,
                "sg": 6.99
            }
        },
        {
            "time": "2022-01-14T01:00:00+00:00",
            "windSpeed": {
                "noaa": 6.53,
                "sg": 6.53
            }
        },
        {
            "time": "2022-01-14T02:00:00+00:00",
            "windSpeed": {
                "noaa": 6.07,
                "sg": 6.07
            }
        },
        {
            "time": "2022-01-14T03:00:00+00:00",
            "windSpeed": {
                "noaa": 5.61,
                "sg": 5.61
            }
        },
        {
            "time": "2022-01-14T04:00:00+00:00",
            "windSpeed": {
                "noaa": 5.46,
                "sg": 5.46
            }
        },
        {
            "time": "2022-01-14T05:00:00+00:00",
            "windSpeed": {
                "noaa": 5.3,
                "sg": 5.3
            }
        },
        {
            "time": "2022-01-14T06:00:00+00:00",
            "windSpeed": {
                "noaa": 5.15,
                "sg": 5.15
            }
        },
        {
            "time": "2022-01-14T07:00:00+00:00",
            "windSpeed": {
                "noaa": 5.39,
                "sg": 5.39
            }
        },
        {
            "time": "2022-01-14T08:00:00+00:00",
            "windSpeed": {
                "noaa": 5.64,
                "sg": 5.64
            }
        },
        {
            "time": "2022-01-14T09:00:00+00:00",
            "windSpeed": {
                "noaa": 5.88,
                "sg": 5.88
            }
        },
        {
            "time": "2022-01-14T10:00:00+00:00",
            "windSpeed": {
                "noaa": 5.61,
                "sg": 5.61
            }
        },
        {
            "time": "2022-01-14T11:00:00+00:00",
            "windSpeed": {
                "noaa": 5.34,
                "sg": 5.34
            }
        },
        {
            "time": "2022-01-14T12:00:00+00:00",
            "windSpeed": {
                "noaa": 5.07,
                "sg": 5.07
            }
        },
        {
            "time": "2022-01-14T13:00:00+00:00",
            "windSpeed": {
                "noaa": 4.94,
                "sg": 4.94
            }
        },
        {
            "time": "2022-01-14T14:00:00+00:00",
            "windSpeed": {
                "noaa": 4.82,
                "sg": 4.82
            }
        },
        {
            "time": "2022-01-14T15:00:00+00:00",
            "windSpeed": {
                "noaa": 4.69,
                "sg": 4.69
            }
        },
        {
            "time": "2022-01-14T16:00:00+00:00",
            "windSpeed": {
                "noaa": 4.8,
                "sg": 4.8
            }
        },
        {
            "time": "2022-01-14T17:00:00+00:00",
            "windSpeed": {
                "noaa": 4.91,
                "sg": 4.91
            }
        },
        {
            "time": "2022-01-14T18:00:00+00:00",
            "windSpeed": {
                "noaa": 5.02,
                "sg": 5.02
            }
        },
        {
            "time": "2022-01-14T19:00:00+00:00",
            "windSpeed": {
                "noaa": 5.12,
                "sg": 5.12
            }
        },
        {
            "time": "2022-01-14T20:00:00+00:00",
            "windSpeed": {
                "noaa": 5.23,
                "sg": 5.23
            }
        },
        {
            "time": "2022-01-14T21:00:00+00:00",
            "windSpeed": {
                "noaa": 5.33,
                "sg": 5.33
            }
        },
        {
            "time": "2022-01-14T22:00:00+00:00",
            "windSpeed": {
                "noaa": 6.1,
                "sg": 6.1
            }
        },
        {
            "time": "2022-01-14T23:00:00+00:00",
            "windSpeed": {
                "noaa": 6.87,
                "sg": 6.87
            }
        },
        {
            "time": "2022-01-15T00:00:00+00:00",
            "windSpeed": {
                "noaa": 7.64,
                "sg": 7.64
            }
        },
        {
            "time": "2022-01-15T01:00:00+00:00",
            "windSpeed": {
                "noaa": 7.53,
                "sg": 7.53
            }
        },
        {
            "time": "2022-01-15T02:00:00+00:00",
            "windSpeed": {
                "noaa": 7.43,
                "sg": 7.43
            }
        },
        {
            "time": "2022-01-15T03:00:00+00:00",
            "windSpeed": {
                "noaa": 7.32,
                "sg": 7.32
            }
        },
        {
            "time": "2022-01-15T04:00:00+00:00",
            "windSpeed": {
                "noaa": 7.41,
                "sg": 7.41
            }
        },
        {
            "time": "2022-01-15T05:00:00+00:00",
            "windSpeed": {
                "noaa": 7.51,
                "sg": 7.51
            }
        },
        {
            "time": "2022-01-15T06:00:00+00:00",
            "windSpeed": {
                "noaa": 7.6,
                "sg": 7.6
            }
        },
        {
            "time": "2022-01-15T07:00:00+00:00",
            "windSpeed": {
                "noaa": 7.41,
                "sg": 7.41
            }
        },
        {
            "time": "2022-01-15T08:00:00+00:00",
            "windSpeed": {
                "noaa": 7.21,
                "sg": 7.21
            }
        },
        {
            "time": "2022-01-15T09:00:00+00:00",
            "windSpeed": {
                "noaa": 7.02,
                "sg": 7.02
            }
        },
        {
            "time": "2022-01-15T10:00:00+00:00",
            "windSpeed": {
                "noaa": 7.46,
                "sg": 7.46
            }
        },
        {
            "time": "2022-01-15T11:00:00+00:00",
            "windSpeed": {
                "noaa": 7.89,
                "sg": 7.89
            }
        },
        {
            "time": "2022-01-15T12:00:00+00:00",
            "windSpeed": {
                "noaa": 8.33,
                "sg": 8.33
            }
        },
        {
            "time": "2022-01-15T13:00:00+00:00",
            "windSpeed": {
                "noaa": 8.41,
                "sg": 8.41
            }
        },
        {
            "time": "2022-01-15T14:00:00+00:00",
            "windSpeed": {
                "noaa": 8.48,
                "sg": 8.48
            }
        },
        {
            "time": "2022-01-15T15:00:00+00:00",
            "windSpeed": {
                "noaa": 8.56,
                "sg": 8.56
            }
        },
        {
            "time": "2022-01-15T16:00:00+00:00",
            "windSpeed": {
                "noaa": 8.42,
                "sg": 8.42
            }
        },
        {
            "time": "2022-01-15T17:00:00+00:00",
            "windSpeed": {
                "noaa": 8.27,
                "sg": 8.27
            }
        },
        {
            "time": "2022-01-15T18:00:00+00:00",
            "windSpeed": {
                "noaa": 8.13,
                "sg": 8.13
            }
        },
        {
            "time": "2022-01-15T19:00:00+00:00",
            "windSpeed": {
                "noaa": 7.89,
                "sg": 7.89
            }
        },
        {
            "time": "2022-01-15T20:00:00+00:00",
            "windSpeed": {
                "noaa": 7.66,
                "sg": 7.66
            }
        },
        {
            "time": "2022-01-15T21:00:00+00:00",
            "windSpeed": {
                "noaa": 7.42,
                "sg": 7.42
            }
        },
        {
            "time": "2022-01-15T22:00:00+00:00",
            "windSpeed": {
                "noaa": 5.86,
                "sg": 5.86
            }
        },
        {
            "time": "2022-01-15T23:00:00+00:00",
            "windSpeed": {
                "noaa": 4.31,
                "sg": 4.31
            }
        },
        {
            "time": "2022-01-16T00:00:00+00:00",
            "windSpeed": {
                "noaa": 2.75,
                "sg": 2.75
            }
        }
    ],
    "meta": {
        "cost": 1,
        "dailyQuota": 10,
        "end": "2022-01-16 00:00",
        "lat": 49.322,
        "lng": -0.012,
        "params": [
            "windSpeed"
        ],
        "requestCount": 1,
        "start": "2022-01-06 00:00"
    }
}
